liverquant/__init__.py
liverquant/colorutil.py
liverquant/liverquant.py
liverquant/slidepatch.py
liverquant-0.0.4.dist-info/LICENSE
liverquant-0.0.4.dist-info/METADATA
liverquant-0.0.4.dist-info/WHEEL
liverquant-0.0.4.dist-info/top_level.txt
liverquant-0.0.4.dist-info/RECORD
