Metadata-Version: 2.1
Name: liverquant
Version: 0.0.4
Summary: Quantitate liver histopathology in whole slide images
Author-email: Mohsen Farzi <mhnfarzi@gmail.com>
Project-URL: Homepage, https://github.com/mfarzi/liverquant
Project-URL: Bug Tracker, https://github.com/mfarzi/liverquant/issues
Keywords: python,geojson,opencv,liver,digital pathology
Classifier: Development Status :: 1 - Planning
Classifier: Programming Language :: Python :: 3
Classifier: License :: OSI Approved :: MIT License
Classifier: Operating System :: OS Independent
Classifier: Intended Audience :: Developers
Classifier: Intended Audience :: Science/Research
Requires-Python: >=3.7
License-File: LICENSE
Requires-Dist: opencv-python
Requires-Dist: numpy
Requires-Dist: geojson
Requires-Dist: cv2geojson
Requires-Dist: openslide-python
Requires-Dist: scikit-image
